<?xml version='1.0' encoding='UTF-8'?>
<?artifactRepository class='org.eclipse.equinox.internal.p2.artifact.repository.simple.SimpleArtifactRepository' version='1.0.0'?>
<repository name='file:/Users/helming/Documents/workspaces/unicase/UnicaseUpdateSite/ - artifacts' type='org.eclipse.equinox.p2.artifact.repository.simpleRepository' version='1.0.0'>
  <properties size='2'>
    <property name='p2.compressed' value='false'/>
    <property name='p2.timestamp' value='1218747982670'/>
  </properties>
  <mappings size='3'>
    <rule filter='(&amp; (classifier=osgi.bundle))' output='${repoUrl}/plugins/${id}_${version}.jar'/>
    <rule filter='(&amp; (classifier=binary))' output='${repoUrl}/binary/${id}_${version}'/>
    <rule filter='(&amp; (classifier=org.eclipse.update.feature))' output='${repoUrl}/features/${id}_${version}.jar'/>
  </mappings>
  <artifacts size='246'>
    <artifact classifier='osgi.bundle' id='org.unicase.ui.tableview' version='0.0.1.200807241052'>
      <properties size='3'>
        <property name='artifact.size' value='9462'/>
        <property name='download.size' value='9462'/>
        <property name='download.contentType' value='application/zip'/>
      </properties>
    </artifact>
    <artifact classifier='osgi.bundle' id='org.unicase.emfstore.esmodel.edit' version='0.0.1.200807151624'>
      <properties size='3'>
        <property name='artifact.size' value='78601'/>
        <property name='download.size' value='78601'/>
        <property name='download.contentType' value='application/zip'/>
      </properties>
    </artifact>
    <artifact classifier='osgi.bundle' id='org.unicase.ui.navigator' version='0.0.2.200807161219'>
      <properties size='3'>
        <property name='artifact.size' value='38145'/>
        <property name='download.size' value='38145'/>
        <property name='download.contentType' value='application/zip'/>
      </properties>
    </artifact>
    <artifact classifier='osgi.bundle' id='org.unicase.ui.test' version='0.0.1.200808142305'>
      <properties size='3'>
        <property name='artifact.size' value='16940'/>
        <property name='download.size' value='16940'/>
        <property name='download.contentType' value='application/zip'/>
      </properties>
    </artifact>
    <artifact classifier='osgi.bundle' id='org.unicase.ui.esbrowser' version='0.0.1.200807151608'>
      <properties size='3'>
        <property name='artifact.size' value='66065'/>
        <property name='download.size' value='66065'/>
        <property name='download.contentType' value='application/zip'/>
      </properties>
    </artifact>
    <artifact classifier='org.eclipse.update.feature' id='org.unicase.client' version='0.1.0'>
      <properties size='2'>
        <property name='artifact.size' value='5286'/>
        <property name='download.size' value='5286'/>
      </properties>
    </artifact>
    <artifact classifier='osgi.bundle' id='org.unicase.ui.navigator' version='0.0.2'>
      <properties size='3'>
        <property name='artifact.size' value='37858'/>
        <property name='download.size' value='37858'/>
        <property name='download.contentType' value='application/zip'/>
      </properties>
    </artifact>
    <artifact classifier='osgi.bundle' id='org.unicase.ui.esbrowser' version='0.0.1.200808121449'>
      <properties size='3'>
        <property name='artifact.size' value='79111'/>
        <property name='download.size' value='79111'/>
        <property name='download.contentType' value='application/zip'/>
      </properties>
    </artifact>
    <artifact classifier='osgi.bundle' id='org.unicase.model.edit' version='0.0.2.200807151624'>
      <properties size='3'>
        <property name='artifact.size' value='251472'/>
        <property name='download.size' value='251472'/>
        <property name='download.contentType' value='application/zip'/>
      </properties>
    </artifact>
    <artifact classifier='osgi.bundle' id='org.unicase.ui.tableview' version='0.0.1.200807151627'>
      <properties size='3'>
        <property name='artifact.size' value='8551'/>
        <property name='download.size' value='8551'/>
        <property name='download.contentType' value='application/zip'/>
      </properties>
    </artifact>
    <artifact classifier='osgi.bundle' id='org.unicase.workspace.edit' version='0.0.1.200808061114'>
      <properties size='3'>
        <property name='artifact.size' value='45216'/>
        <property name='download.size' value='45216'/>
        <property name='download.contentType' value='application/zip'/>
      </properties>
    </artifact>
    <artifact classifier='org.eclipse.update.feature' id='org.unicase.client' version='0.0.7'>
      <properties size='2'>
        <property name='artifact.size' value='1132'/>
        <property name='download.size' value='1132'/>
      </properties>
    </artifact>
    <artifact classifier='osgi.bundle' id='org.unicase.ui.navigator' version='0.1.0'>
      <properties size='3'>
        <property name='artifact.size' value='42100'/>
        <property name='download.size' value='42100'/>
        <property name='download.contentType' value='application/zip'/>
      </properties>
    </artifact>
    <artifact classifier='osgi.bundle' id='org.unicase.ui.navigator' version='0.0.2.200807241052'>
      <properties size='3'>
        <property name='artifact.size' value='43734'/>
        <property name='download.size' value='43734'/>
        <property name='download.contentType' value='application/zip'/>
      </properties>
    </artifact>
    <artifact classifier='org.eclipse.update.feature' id='org.unicase.client' version='0.0.4'>
      <properties size='2'>
        <property name='artifact.size' value='1083'/>
        <property name='download.size' value='1083'/>
      </properties>
    </artifact>
    <artifact classifier='osgi.bundle' id='org.unicase.ui.common' version='0.0.1.200807151624'>
      <properties size='3'>
        <property name='artifact.size' value='7596'/>
        <property name='download.size' value='7596'/>
        <property name='download.contentType' value='application/zip'/>
      </properties>
    </artifact>
    <artifact classifier='osgi.bundle' id='org.unicase.emfstore.esmodel' version='0.0.1.200807151627'>
      <properties size='3'>
        <property name='artifact.size' value='102152'/>
        <property name='download.size' value='102152'/>
        <property name='download.contentType' value='application/zip'/>
      </properties>
    </artifact>
    <artifact classifier='osgi.bundle' id='org.unicase.ui.meeditor' version='0.0.1.200807171123'>
      <properties size='3'>
        <property name='artifact.size' value='47631'/>
        <property name='download.size' value='47631'/>
        <property name='download.contentType' value='application/zip'/>
      </properties>
    </artifact>
    <artifact classifier='osgi.bundle' id='org.unicase.ui.navigator' version='0.0.2.200807151618'>
      <properties size='3'>
        <property name='artifact.size' value='38146'/>
        <property name='download.size' value='38146'/>
        <property name='download.contentType' value='application/zip'/>
      </properties>
    </artifact>
    <artifact classifier='org.eclipse.update.feature' id='org.unicase.client' version='0.0.14'>
      <properties size='2'>
        <property name='artifact.size' value='5282'/>
        <property name='download.size' value='5282'/>
      </properties>
    </artifact>
    <artifact classifier='osgi.bundle' id='org.unicase.ui.tableview' version='0.0.1.200807161219'>
      <properties size='3'>
        <property name='artifact.size' value='8550'/>
        <property name='download.size' value='8550'/>
        <property name='download.contentType' value='application/zip'/>
      </properties>
    </artifact>
    <artifact classifier='osgi.bundle' id='org.unicase.workspace' version='0.0.1.200807171123'>
      <properties size='3'>
        <property name='artifact.size' value='50713'/>
        <property name='download.size' value='50713'/>
        <property name='download.contentType' value='application/zip'/>
      </properties>
    </artifact>
    <artifact classifier='osgi.bundle' id='org.unicase.ui.navigator' version='0.0.2.200808061751'>
      <properties size='3'>
        <property name='artifact.size' value='44472'/>
        <property name='download.size' value='44472'/>
        <property name='download.contentType' value='application/zip'/>
      </properties>
    </artifact>
    <artifact classifier='osgi.bundle' id='org.unicase.emfstore.esmodel.edit' version='0.0.1.200807151615'>
      <properties size='3'>
        <property name='artifact.size' value='78598'/>
        <property name='download.size' value='78598'/>
        <property name='download.contentType' value='application/zip'/>
      </properties>
    </artifact>
    <artifact classifier='org.eclipse.update.feature' id='org.unicase.client' version='0.0.1'>
      <properties size='2'>
        <property name='artifact.size' value='1130'/>
        <property name='download.size' value='1130'/>
      </properties>
    </artifact>
    <artifact classifier='osgi.bundle' id='org.unicase.ui.stem' version='0.0.1'>
      <properties size='3'>
        <property name='artifact.size' value='10768'/>
        <property name='download.size' value='10768'/>
        <property name='download.contentType' value='application/zip'/>
      </properties>
    </artifact>
    <artifact classifier='osgi.bundle' id='org.unicase.ui.meeditor' version='0.0.1.200807151615'>
      <properties size='3'>
        <property name='artifact.size' value='45277'/>
        <property name='download.size' value='45277'/>
        <property name='download.contentType' value='application/zip'/>
      </properties>
    </artifact>
    <artifact classifier='osgi.bundle' id='org.unicase.workspace' version='0.0.1'>
      <properties size='3'>
        <property name='artifact.size' value='53231'/>
        <property name='download.size' value='53231'/>
        <property name='download.contentType' value='application/zip'/>
      </properties>
    </artifact>
    <artifact classifier='osgi.bundle' id='org.unicase.model' version='0.0.1.200807161219'>
      <properties size='3'>
        <property name='artifact.size' value='322993'/>
        <property name='download.size' value='322993'/>
        <property name='download.contentType' value='application/zip'/>
      </properties>
    </artifact>
    <artifact classifier='org.eclipse.update.feature' id='org.unicase.client' version='0.0.9'>
      <properties size='2'>
        <property name='artifact.size' value='5275'/>
        <property name='download.size' value='5275'/>
      </properties>
    </artifact>
    <artifact classifier='osgi.bundle' id='org.unicase.ui.tableview' version='0.0.1'>
      <properties size='3'>
        <property name='artifact.size' value='8532'/>
        <property name='download.size' value='8532'/>
        <property name='download.contentType' value='application/zip'/>
      </properties>
    </artifact>
    <artifact classifier='osgi.bundle' id='org.unicase.ui.meeditor' version='0.0.1.200807241052'>
      <properties size='3'>
        <property name='artifact.size' value='47718'/>
        <property name='download.size' value='47718'/>
        <property name='download.contentType' value='application/zip'/>
      </properties>
    </artifact>
    <artifact classifier='osgi.bundle' id='org.unicase.workspace.edit' version='0.0.1.200808061744'>
      <properties size='3'>
        <property name='artifact.size' value='45212'/>
        <property name='download.size' value='45212'/>
        <property name='download.contentType' value='application/zip'/>
      </properties>
    </artifact>
    <artifact classifier='osgi.bundle' id='org.unicase.workspace.edit' version='0.0.1'>
      <properties size='3'>
        <property name='artifact.size' value='26943'/>
        <property name='download.size' value='26943'/>
        <property name='download.contentType' value='application/zip'/>
      </properties>
    </artifact>
    <artifact classifier='osgi.bundle' id='org.unicase.ui.meeditor' version='0.0.1.200807151624'>
      <properties size='3'>
        <property name='artifact.size' value='45277'/>
        <property name='download.size' value='45277'/>
        <property name='download.contentType' value='application/zip'/>
      </properties>
    </artifact>
    <artifact classifier='osgi.bundle' id='org.unicase.ui.navigator' version='0.0.2.200808061114'>
      <properties size='3'>
        <property name='artifact.size' value='44472'/>
        <property name='download.size' value='44472'/>
        <property name='download.contentType' value='application/zip'/>
      </properties>
    </artifact>
    <artifact classifier='osgi.bundle' id='org.unicase.ui.navigator' version='0.0.2.200807171123'>
      <properties size='3'>
        <property name='artifact.size' value='38145'/>
        <property name='download.size' value='38145'/>
        <property name='download.contentType' value='application/zip'/>
      </properties>
    </artifact>
    <artifact classifier='osgi.bundle' id='org.unicase.ui.test' version='0.0.1.200807171123'>
      <properties size='3'>
        <property name='artifact.size' value='16552'/>
        <property name='download.size' value='16552'/>
        <property name='download.contentType' value='application/zip'/>
      </properties>
    </artifact>
    <artifact classifier='osgi.bundle' id='org.unicase.emfstore.esmodel' version='0.0.1.200807151615'>
      <properties size='3'>
        <property name='artifact.size' value='102152'/>
        <property name='download.size' value='102152'/>
        <property name='download.contentType' value='application/zip'/>
      </properties>
    </artifact>
    <artifact classifier='osgi.bundle' id='org.unicase.model' version='0.0.1.200808061751'>
      <properties size='3'>
        <property name='artifact.size' value='338848'/>
        <property name='download.size' value='338848'/>
        <property name='download.contentType' value='application/zip'/>
      </properties>
    </artifact>
    <artifact classifier='osgi.bundle' id='org.unicase.emfstore' version='0.0.1.200808061744'>
      <properties size='3'>
        <property name='artifact.size' value='3827384'/>
        <property name='download.size' value='3827384'/>
        <property name='download.contentType' value='application/zip'/>
      </properties>
    </artifact>
    <artifact classifier='osgi.bundle' id='org.unicase.emfstore.esmodel.edit' version='0.0.1.200808142305'>
      <properties size='3'>
        <property name='artifact.size' value='103338'/>
        <property name='download.size' value='103338'/>
        <property name='download.contentType' value='application/zip'/>
      </properties>
    </artifact>
    <artifact classifier='osgi.bundle' id='org.unicase.emfstore' version='0.0.1.200807171123'>
      <properties size='3'>
        <property name='artifact.size' value='3809480'/>
        <property name='download.size' value='3809480'/>
        <property name='download.contentType' value='application/zip'/>
      </properties>
    </artifact>
    <artifact classifier='osgi.bundle' id='org.unicase.ui.esbrowser' version='0.0.1'>
      <properties size='3'>
        <property name='artifact.size' value='64995'/>
        <property name='download.size' value='64995'/>
        <property name='download.contentType' value='application/zip'/>
      </properties>
    </artifact>
    <artifact classifier='org.eclipse.update.feature' id='org.unicase.client' version='0.0.5'>
      <properties size='2'>
        <property name='artifact.size' value='1106'/>
        <property name='download.size' value='1106'/>
      </properties>
    </artifact>
    <artifact classifier='osgi.bundle' id='org.unicase.ui.navigator' version='0.0.2.200807151624'>
      <properties size='3'>
        <property name='artifact.size' value='38146'/>
        <property name='download.size' value='38146'/>
        <property name='download.contentType' value='application/zip'/>
      </properties>
    </artifact>
    <artifact classifier='osgi.bundle' id='org.unicase.ui.esbrowser' version='0.0.1.200808061744'>
      <properties size='3'>
        <property name='artifact.size' value='77085'/>
        <property name='download.size' value='77085'/>
        <property name='download.contentType' value='application/zip'/>
      </properties>
    </artifact>
    <artifact classifier='osgi.bundle' id='org.unicase.ui.stem' version='0.0.1.200808061751'>
      <properties size='3'>
        <property name='artifact.size' value='23039'/>
        <property name='download.size' value='23039'/>
        <property name='download.contentType' value='application/zip'/>
      </properties>
    </artifact>
    <artifact classifier='osgi.bundle' id='org.unicase.model.edit' version='0.0.2.200807241052'>
      <properties size='3'>
        <property name='artifact.size' value='238993'/>
        <property name='download.size' value='238993'/>
        <property name='download.contentType' value='application/zip'/>
      </properties>
    </artifact>
    <artifact classifier='osgi.bundle' id='org.unicase.emfstore.esmodel.edit' version='0.0.1.200807171123'>
      <properties size='3'>
        <property name='artifact.size' value='78601'/>
        <property name='download.size' value='78601'/>
        <property name='download.contentType' value='application/zip'/>
      </properties>
    </artifact>
    <artifact classifier='osgi.bundle' id='org.unicase.model' version='0.0.1.200808061744'>
      <properties size='3'>
        <property name='artifact.size' value='338848'/>
        <property name='download.size' value='338848'/>
        <property name='download.contentType' value='application/zip'/>
      </properties>
    </artifact>
    <artifact classifier='osgi.bundle' id='org.unicase.workspace' version='0.0.1.200807241052'>
      <properties size='3'>
        <property name='artifact.size' value='56632'/>
        <property name='download.size' value='56632'/>
        <property name='download.contentType' value='application/zip'/>
      </properties>
    </artifact>
    <artifact classifier='osgi.bundle' id='org.unicase.emfstore' version='0.0.1.200807241052'>
      <properties size='3'>
        <property name='artifact.size' value='3812981'/>
        <property name='download.size' value='3812981'/>
        <property name='download.contentType' value='application/zip'/>
      </properties>
    </artifact>
    <artifact classifier='osgi.bundle' id='org.unicase.ui.stem' version='0.0.1.200808121449'>
      <properties size='3'>
        <property name='artifact.size' value='27767'/>
        <property name='download.size' value='27767'/>
        <property name='download.contentType' value='application/zip'/>
      </properties>
    </artifact>
    <artifact classifier='osgi.bundle' id='org.unicase.workspace.edit' version='0.0.1.200808061751'>
      <properties size='3'>
        <property name='artifact.size' value='45216'/>
        <property name='download.size' value='45216'/>
        <property name='download.contentType' value='application/zip'/>
      </properties>
    </artifact>
    <artifact classifier='osgi.bundle' id='org.unicase.emfstore' version='0.0.1.200807151615'>
      <properties size='3'>
        <property name='artifact.size' value='3809185'/>
        <property name='download.size' value='3809185'/>
        <property name='download.contentType' value='application/zip'/>
      </properties>
    </artifact>
    <artifact classifier='osgi.bundle' id='org.unicase.ui.test' version='0.0.1'>
      <properties size='3'>
        <property name='artifact.size' value='16316'/>
        <property name='download.size' value='16316'/>
        <property name='download.contentType' value='application/zip'/>
      </properties>
    </artifact>
    <artifact classifier='osgi.bundle' id='org.unicase.ui.tableview' version='0.0.1.200807221110'>
      <properties size='3'>
        <property name='artifact.size' value='9462'/>
        <property name='download.size' value='9462'/>
        <property name='download.contentType' value='application/zip'/>
      </properties>
    </artifact>
    <artifact classifier='osgi.bundle' id='org.unicase.model.edit' version='0.0.2.200808061731'>
      <properties size='3'>
        <property name='artifact.size' value='240358'/>
        <property name='download.size' value='240358'/>
        <property name='download.contentType' value='application/zip'/>
      </properties>
    </artifact>
    <artifact classifier='osgi.bundle' id='org.unicase.workspace' version='0.0.1'>
      <properties size='3'>
        <property name='artifact.size' value='53229'/>
        <property name='download.size' value='53229'/>
        <property name='download.contentType' value='application/zip'/>
      </properties>
    </artifact>
    <artifact classifier='osgi.bundle' id='org.unicase.ui.esbrowser' version='0.0.1.200807151615'>
      <properties size='3'>
        <property name='artifact.size' value='66065'/>
        <property name='download.size' value='66065'/>
        <property name='download.contentType' value='application/zip'/>
      </properties>
    </artifact>
    <artifact classifier='osgi.bundle' id='org.unicase.ui.common' version='0.0.1.200807171123'>
      <properties size='3'>
        <property name='artifact.size' value='16014'/>
        <property name='download.size' value='16014'/>
        <property name='download.contentType' value='application/zip'/>
      </properties>
    </artifact>
    <artifact classifier='osgi.bundle' id='org.unicase.model' version='0.0.1.200807151608'>
      <properties size='3'>
        <property name='artifact.size' value='322993'/>
        <property name='download.size' value='322993'/>
        <property name='download.contentType' value='application/zip'/>
      </properties>
    </artifact>
    <artifact classifier='osgi.bundle' id='org.eclipse.nebula.widgets.gantchart' version='0.0.14'>
      <properties size='3'>
        <property name='artifact.size' value='292055'/>
        <property name='download.size' value='292055'/>
        <property name='download.contentType' value='application/zip'/>
      </properties>
    </artifact>
    <artifact classifier='osgi.bundle' id='org.unicase.emfstore' version='0.0.1.200808142305'>
      <properties size='3'>
        <property name='artifact.size' value='3848759'/>
        <property name='download.size' value='3848759'/>
        <property name='download.contentType' value='application/zip'/>
      </properties>
    </artifact>
    <artifact classifier='osgi.bundle' id='org.unicase.ui.test' version='0.0.1.200807161219'>
      <properties size='3'>
        <property name='artifact.size' value='16552'/>
        <property name='download.size' value='16552'/>
        <property name='download.contentType' value='application/zip'/>
      </properties>
    </artifact>
    <artifact classifier='osgi.bundle' id='org.unicase.ui.tableview' version='0.0.1.200807151620'>
      <properties size='3'>
        <property name='artifact.size' value='8550'/>
        <property name='download.size' value='8550'/>
        <property name='download.contentType' value='application/zip'/>
      </properties>
    </artifact>
    <artifact classifier='osgi.bundle' id='org.unicase.model' version='0.0.1.200808121449'>
      <properties size='3'>
        <property name='artifact.size' value='366712'/>
        <property name='download.size' value='366712'/>
        <property name='download.contentType' value='application/zip'/>
      </properties>
    </artifact>
    <artifact classifier='osgi.bundle' id='org.unicase.ui.test' version='0.0.1.200808121449'>
      <properties size='3'>
        <property name='artifact.size' value='16940'/>
        <property name='download.size' value='16940'/>
        <property name='download.contentType' value='application/zip'/>
      </properties>
    </artifact>
    <artifact classifier='osgi.bundle' id='org.unicase.ui.esbrowser' version='0.0.1.200807221110'>
      <properties size='3'>
        <property name='artifact.size' value='66125'/>
        <property name='download.size' value='66125'/>
        <property name='download.contentType' value='application/zip'/>
      </properties>
    </artifact>
    <artifact classifier='osgi.bundle' id='org.unicase.emfstore.esmodel.edit' version='0.0.1.200807241052'>
      <properties size='3'>
        <property name='artifact.size' value='101281'/>
        <property name='download.size' value='101281'/>
        <property name='download.contentType' value='application/zip'/>
      </properties>
    </artifact>
    <artifact classifier='osgi.bundle' id='org.unicase.model.edit' version='0.0.2.200807151608'>
      <properties size='3'>
        <property name='artifact.size' value='251471'/>
        <property name='download.size' value='251471'/>
        <property name='download.contentType' value='application/zip'/>
      </properties>
    </artifact>
    <artifact classifier='osgi.bundle' id='org.unicase.ui.esbrowser' version='0.0.1.200807151618'>
      <properties size='3'>
        <property name='artifact.size' value='66065'/>
        <property name='download.size' value='66065'/>
        <property name='download.contentType' value='application/zip'/>
      </properties>
    </artifact>
    <artifact classifier='osgi.bundle' id='org.unicase.ui.meeditor' version='0.0.1.200807151627'>
      <properties size='3'>
        <property name='artifact.size' value='45277'/>
        <property name='download.size' value='45277'/>
        <property name='download.contentType' value='application/zip'/>
      </properties>
    </artifact>
    <artifact classifier='osgi.bundle' id='org.unicase.model.edit' version='0.0.2.200807171123'>
      <properties size='3'>
        <property name='artifact.size' value='246512'/>
        <property name='download.size' value='246512'/>
        <property name='download.contentType' value='application/zip'/>
      </properties>
    </artifact>
    <artifact classifier='osgi.bundle' id='org.unicase.emfstore.esmodel.edit' version='0.0.1.200808061751'>
      <properties size='3'>
        <property name='artifact.size' value='103340'/>
        <property name='download.size' value='103340'/>
        <property name='download.contentType' value='application/zip'/>
      </properties>
    </artifact>
    <artifact classifier='osgi.bundle' id='org.unicase.ui.test' version='0.0.1.200808061114'>
      <properties size='3'>
        <property name='artifact.size' value='16939'/>
        <property name='download.size' value='16939'/>
        <property name='download.contentType' value='application/zip'/>
      </properties>
    </artifact>
    <artifact classifier='osgi.bundle' id='org.unicase.ui.test' version='0.0.1.200808061751'>
      <properties size='3'>
        <property name='artifact.size' value='16940'/>
        <property name='download.size' value='16940'/>
        <property name='download.contentType' value='application/zip'/>
      </properties>
    </artifact>
    <artifact classifier='org.eclipse.update.feature' id='org.unicase.client' version='0.0.4'>
      <properties size='2'>
        <property name='artifact.size' value='1088'/>
        <property name='download.size' value='1088'/>
      </properties>
    </artifact>
    <artifact classifier='org.eclipse.update.feature' id='org.unicase.client' version='0.0.1'>
      <properties size='2'>
        <property name='artifact.size' value='1035'/>
        <property name='download.size' value='1035'/>
      </properties>
    </artifact>
    <artifact classifier='osgi.bundle' id='org.unicase.ui.common' version='0.0.1.200807221110'>
      <properties size='3'>
        <property name='artifact.size' value='32279'/>
        <property name='download.size' value='32279'/>
        <property name='download.contentType' value='application/zip'/>
      </properties>
    </artifact>
    <artifact classifier='org.eclipse.update.feature' id='org.unicase.client' version='0.0.12'>
      <properties size='2'>
        <property name='artifact.size' value='5281'/>
        <property name='download.size' value='5281'/>
      </properties>
    </artifact>
    <artifact classifier='osgi.bundle' id='org.unicase.ui.tableview' version='0.0.1.200807151624'>
      <properties size='3'>
        <property name='artifact.size' value='8551'/>
        <property name='download.size' value='8551'/>
        <property name='download.contentType' value='application/zip'/>
      </properties>
    </artifact>
    <artifact classifier='osgi.bundle' id='org.unicase.emfstore.esmodel.edit' version='0.0.1.200808121449'>
      <properties size='3'>
        <property name='artifact.size' value='103341'/>
        <property name='download.size' value='103341'/>
        <property name='download.contentType' value='application/zip'/>
      </properties>
    </artifact>
    <artifact classifier='osgi.bundle' id='org.eclipse.nebula.widgets.gantchart' version='1.0.0'>
      <properties size='3'>
        <property name='artifact.size' value='292051'/>
        <property name='download.size' value='292051'/>
        <property name='download.contentType' value='application/zip'/>
      </properties>
    </artifact>
    <artifact classifier='osgi.bundle' id='org.unicase.workspace.edit' version='0.0.1.200807241052'>
      <properties size='3'>
        <property name='artifact.size' value='45107'/>
        <property name='download.size' value='45107'/>
        <property name='download.contentType' value='application/zip'/>
      </properties>
    </artifact>
    <artifact classifier='osgi.bundle' id='org.unicase.ui.meeditor' version='0.0.1.200808061751'>
      <properties size='3'>
        <property name='artifact.size' value='48446'/>
        <property name='download.size' value='48446'/>
        <property name='download.contentType' value='application/zip'/>
      </properties>
    </artifact>
    <artifact classifier='osgi.bundle' id='org.unicase.emfstore.esmodel' version='0.0.1.200807221110'>
      <properties size='3'>
        <property name='artifact.size' value='102450'/>
        <property name='download.size' value='102450'/>
        <property name='download.contentType' value='application/zip'/>
      </properties>
    </artifact>
    <artifact classifier='osgi.bundle' id='org.unicase.ui.esbrowser' version='0.0.1.200807171123'>
      <properties size='3'>
        <property name='artifact.size' value='66065'/>
        <property name='download.size' value='66065'/>
        <property name='download.contentType' value='application/zip'/>
      </properties>
    </artifact>
    <artifact classifier='osgi.bundle' id='org.unicase.emfstore.esmodel.edit' version='0.0.1.200807151608'>
      <properties size='3'>
        <property name='artifact.size' value='78601'/>
        <property name='download.size' value='78601'/>
        <property name='download.contentType' value='application/zip'/>
      </properties>
    </artifact>
    <artifact classifier='osgi.bundle' id='org.unicase.model.edit' version='0.0.2.200808061751'>
      <properties size='3'>
        <property name='artifact.size' value='240358'/>
        <property name='download.size' value='240358'/>
        <property name='download.contentType' value='application/zip'/>
      </properties>
    </artifact>
    <artifact classifier='osgi.bundle' id='org.unicase.ui.stem' version='0.0.1.200808061731'>
      <properties size='3'>
        <property name='artifact.size' value='23039'/>
        <property name='download.size' value='23039'/>
        <property name='download.contentType' value='application/zip'/>
      </properties>
    </artifact>
    <artifact classifier='osgi.bundle' id='org.unicase.ui.navigator' version='0.0.2.200807221110'>
      <properties size='3'>
        <property name='artifact.size' value='44519'/>
        <property name='download.size' value='44519'/>
        <property name='download.contentType' value='application/zip'/>
      </properties>
    </artifact>
    <artifact classifier='osgi.bundle' id='org.unicase.emfstore.esmodel' version='0.0.1.200808121449'>
      <properties size='3'>
        <property name='artifact.size' value='149248'/>
        <property name='download.size' value='149248'/>
        <property name='download.contentType' value='application/zip'/>
      </properties>
    </artifact>
    <artifact classifier='osgi.bundle' id='org.unicase.workspace' version='0.0.1.200808061744'>
      <properties size='3'>
        <property name='artifact.size' value='64748'/>
        <property name='download.size' value='64748'/>
        <property name='download.contentType' value='application/zip'/>
      </properties>
    </artifact>
    <artifact classifier='osgi.bundle' id='org.unicase.ui.navigator' version='0.0.2.200808061744'>
      <properties size='3'>
        <property name='artifact.size' value='44473'/>
        <property name='download.size' value='44473'/>
        <property name='download.contentType' value='application/zip'/>
      </properties>
    </artifact>
    <artifact classifier='osgi.bundle' id='org.unicase.emfstore.esmodel' version='0.0.1.200808142305'>
      <properties size='3'>
        <property name='artifact.size' value='149276'/>
        <property name='download.size' value='149276'/>
        <property name='download.contentType' value='application/zip'/>
      </properties>
    </artifact>
    <artifact classifier='osgi.bundle' id='org.unicase.workspace' version='0.0.1.200808061751'>
      <properties size='3'>
        <property name='artifact.size' value='64747'/>
        <property name='download.size' value='64747'/>
        <property name='download.contentType' value='application/zip'/>
      </properties>
    </artifact>
    <artifact classifier='osgi.bundle' id='org.unicase.ui.tableview' version='0.0.1.200808061744'>
      <properties size='3'>
        <property name='artifact.size' value='16799'/>
        <property name='download.size' value='16799'/>
        <property name='download.contentType' value='application/zip'/>
      </properties>
    </artifact>
    <artifact classifier='osgi.bundle' id='org.unicase.workspace.edit' version='0.0.1.200807171123'>
      <properties size='3'>
        <property name='artifact.size' value='28006'/>
        <property name='download.size' value='28006'/>
        <property name='download.contentType' value='application/zip'/>
      </properties>
    </artifact>
    <artifact classifier='osgi.bundle' id='org.unicase.model.edit' version='0.0.2.200808142305'>
      <properties size='3'>
        <property name='artifact.size' value='257374'/>
        <property name='download.size' value='257374'/>
        <property name='download.contentType' value='application/zip'/>
      </properties>
    </artifact>
    <artifact classifier='osgi.bundle' id='org.unicase.ui.navigator' version='0.0.2.200807151608'>
      <properties size='3'>
        <property name='artifact.size' value='38146'/>
        <property name='download.size' value='38146'/>
        <property name='download.contentType' value='application/zip'/>
      </properties>
    </artifact>
    <artifact classifier='osgi.bundle' id='org.unicase.emfstore' version='0.0.1'>
      <properties size='3'>
        <property name='artifact.size' value='3809656'/>
        <property name='download.size' value='3809656'/>
        <property name='download.contentType' value='application/zip'/>
      </properties>
    </artifact>
    <artifact classifier='osgi.bundle' id='org.unicase.emfstore' version='0.0.1.200807151618'>
      <properties size='3'>
        <property name='artifact.size' value='3809184'/>
        <property name='download.size' value='3809184'/>
        <property name='download.contentType' value='application/zip'/>
      </properties>
    </artifact>
    <artifact classifier='osgi.bundle' id='org.unicase.workspace.edit' version='0.0.1.qualfier'>
      <properties size='3'>
        <property name='artifact.size' value='26931'/>
        <property name='download.size' value='26931'/>
        <property name='download.contentType' value='application/zip'/>
      </properties>
    </artifact>
    <artifact classifier='osgi.bundle' id='org.unicase.ui.navigator' version='0.0.2.200807151627'>
      <properties size='3'>
        <property name='artifact.size' value='38146'/>
        <property name='download.size' value='38146'/>
        <property name='download.contentType' value='application/zip'/>
      </properties>
    </artifact>
    <artifact classifier='osgi.bundle' id='org.unicase.ui.navigator' version='0.0.2'>
      <properties size='3'>
        <property name='artifact.size' value='37896'/>
        <property name='download.size' value='37896'/>
        <property name='download.contentType' value='application/zip'/>
      </properties>
    </artifact>
    <artifact classifier='osgi.bundle' id='org.unicase.emfstore.esmodel.edit' version='0.0.1.200807151618'>
      <properties size='3'>
        <property name='artifact.size' value='78601'/>
        <property name='download.size' value='78601'/>
        <property name='download.contentType' value='application/zip'/>
      </properties>
    </artifact>
    <artifact classifier='osgi.bundle' id='org.unicase.ui.common' version='0.0.1.200807151618'>
      <properties size='3'>
        <property name='artifact.size' value='7596'/>
        <property name='download.size' value='7596'/>
        <property name='download.contentType' value='application/zip'/>
      </properties>
    </artifact>
    <artifact classifier='osgi.bundle' id='org.unicase.ui.meeditor' version='0.0.1.200808142305'>
      <properties size='3'>
        <property name='artifact.size' value='47969'/>
        <property name='download.size' value='47969'/>
        <property name='download.contentType' value='application/zip'/>
      </properties>
    </artifact>
    <artifact classifier='osgi.bundle' id='org.unicase.ui.navigator' version='0.0.2'>
      <properties size='3'>
        <property name='artifact.size' value='47117'/>
        <property name='download.size' value='47117'/>
        <property name='download.contentType' value='application/zip'/>
      </properties>
    </artifact>
    <artifact classifier='osgi.bundle' id='org.unicase.ui.common' version='0.0.1.200808061751'>
      <properties size='3'>
        <property name='artifact.size' value='30895'/>
        <property name='download.size' value='30895'/>
        <property name='download.contentType' value='application/zip'/>
      </properties>
    </artifact>
    <artifact classifier='osgi.bundle' id='org.unicase.model' version='0.0.1.200808061731'>
      <properties size='3'>
        <property name='artifact.size' value='338848'/>
        <property name='download.size' value='338848'/>
        <property name='download.contentType' value='application/zip'/>
      </properties>
    </artifact>
    <artifact classifier='osgi.bundle' id='org.unicase.emfstore' version='0.0.1.200807151620'>
      <properties size='3'>
        <property name='artifact.size' value='3809185'/>
        <property name='download.size' value='3809185'/>
        <property name='download.contentType' value='application/zip'/>
      </properties>
    </artifact>
    <artifact classifier='osgi.bundle' id='org.unicase.ui.meeditor' version='0.0.1.200807221110'>
      <properties size='3'>
        <property name='artifact.size' value='47683'/>
        <property name='download.size' value='47683'/>
        <property name='download.contentType' value='application/zip'/>
      </properties>
    </artifact>
    <artifact classifier='osgi.bundle' id='org.unicase.ui.test' version='0.0.1.200808061731'>
      <properties size='3'>
        <property name='artifact.size' value='16940'/>
        <property name='download.size' value='16940'/>
        <property name='download.contentType' value='application/zip'/>
      </properties>
    </artifact>
    <artifact classifier='osgi.bundle' id='org.unicase.ui.common' version='0.0.1.200808061114'>
      <properties size='3'>
        <property name='artifact.size' value='30894'/>
        <property name='download.size' value='30894'/>
        <property name='download.contentType' value='application/zip'/>
      </properties>
    </artifact>
    <artifact classifier='osgi.bundle' id='org.unicase.emfstore.esmodel' version='0.0.1.200808061114'>
      <properties size='3'>
        <property name='artifact.size' value='147165'/>
        <property name='download.size' value='147165'/>
        <property name='download.contentType' value='application/zip'/>
      </properties>
    </artifact>
    <artifact classifier='osgi.bundle' id='org.unicase.ui.navigator' version='0.0.2'>
      <properties size='3'>
        <property name='artifact.size' value='56160'/>
        <property name='download.size' value='56160'/>
        <property name='download.contentType' value='application/zip'/>
      </properties>
    </artifact>
    <artifact classifier='osgi.bundle' id='org.unicase.ui.tableview' version='0.0.1.200807151608'>
      <properties size='3'>
        <property name='artifact.size' value='8551'/>
        <property name='download.size' value='8551'/>
        <property name='download.contentType' value='application/zip'/>
      </properties>
    </artifact>
    <artifact classifier='osgi.bundle' id='org.unicase.model' version='0.0.1.200807151624'>
      <properties size='3'>
        <property name='artifact.size' value='322994'/>
        <property name='download.size' value='322994'/>
        <property name='download.contentType' value='application/zip'/>
      </properties>
    </artifact>
    <artifact classifier='osgi.bundle' id='org.unicase.emfstore' version='0.0.1.200808061751'>
      <properties size='3'>
        <property name='artifact.size' value='3827383'/>
        <property name='download.size' value='3827383'/>
        <property name='download.contentType' value='application/zip'/>
      </properties>
    </artifact>
    <artifact classifier='osgi.bundle' id='org.unicase.ui.stem' version='0.0.1.200808142305'>
      <properties size='3'>
        <property name='artifact.size' value='27812'/>
        <property name='download.size' value='27812'/>
        <property name='download.contentType' value='application/zip'/>
      </properties>
    </artifact>
    <artifact classifier='osgi.bundle' id='org.unicase.emfstore' version='0.0.1.200808121449'>
      <properties size='3'>
        <property name='artifact.size' value='3845188'/>
        <property name='download.size' value='3845188'/>
        <property name='download.contentType' value='application/zip'/>
      </properties>
    </artifact>
    <artifact classifier='osgi.bundle' id='org.unicase.emfstore.esmodel' version='0.0.1.200807171123'>
      <properties size='3'>
        <property name='artifact.size' value='102450'/>
        <property name='download.size' value='102450'/>
        <property name='download.contentType' value='application/zip'/>
      </properties>
    </artifact>
    <artifact classifier='osgi.bundle' id='org.unicase.emfstore.esmodel' version='0.0.1.200808061731'>
      <properties size='3'>
        <property name='artifact.size' value='147258'/>
        <property name='download.size' value='147258'/>
        <property name='download.contentType' value='application/zip'/>
      </properties>
    </artifact>
    <artifact classifier='osgi.bundle' id='org.unicase.ui.meeditor' version='0.0.1.200808061731'>
      <properties size='3'>
        <property name='artifact.size' value='48446'/>
        <property name='download.size' value='48446'/>
        <property name='download.contentType' value='application/zip'/>
      </properties>
    </artifact>
    <artifact classifier='osgi.bundle' id='org.unicase.emfstore.esmodel' version='0.0.1'>
      <properties size='3'>
        <property name='artifact.size' value='132885'/>
        <property name='download.size' value='132885'/>
        <property name='download.contentType' value='application/zip'/>
      </properties>
    </artifact>
    <artifact classifier='org.eclipse.update.feature' id='org.unicase.client' version='0.0.4'>
      <properties size='2'>
        <property name='artifact.size' value='1106'/>
        <property name='download.size' value='1106'/>
      </properties>
    </artifact>
    <artifact classifier='osgi.bundle' id='org.unicase.ui.test' version='0.0.1.200808061744'>
      <properties size='3'>
        <property name='artifact.size' value='16941'/>
        <property name='download.size' value='16941'/>
        <property name='download.contentType' value='application/zip'/>
      </properties>
    </artifact>
    <artifact classifier='osgi.bundle' id='org.unicase.workspace' version='0.0.1.200807221110'>
      <properties size='3'>
        <property name='artifact.size' value='56554'/>
        <property name='download.size' value='56554'/>
        <property name='download.contentType' value='application/zip'/>
      </properties>
    </artifact>
    <artifact classifier='osgi.bundle' id='org.unicase.ui.esbrowser' version='0.0.1.200807151620'>
      <properties size='3'>
        <property name='artifact.size' value='66066'/>
        <property name='download.size' value='66066'/>
        <property name='download.contentType' value='application/zip'/>
      </properties>
    </artifact>
    <artifact classifier='osgi.bundle' id='org.unicase.emfstore' version='0.0.1.200807151624'>
      <properties size='3'>
        <property name='artifact.size' value='3809184'/>
        <property name='download.size' value='3809184'/>
        <property name='download.contentType' value='application/zip'/>
      </properties>
    </artifact>
    <artifact classifier='osgi.bundle' id='org.unicase.model' version='0.0.1.200807221110'>
      <properties size='3'>
        <property name='artifact.size' value='321755'/>
        <property name='download.size' value='321755'/>
        <property name='download.contentType' value='application/zip'/>
      </properties>
    </artifact>
    <artifact classifier='osgi.bundle' id='org.unicase.model' version='0.0.1'>
      <properties size='3'>
        <property name='artifact.size' value='304708'/>
        <property name='download.size' value='304708'/>
        <property name='download.contentType' value='application/zip'/>
      </properties>
    </artifact>
    <artifact classifier='osgi.bundle' id='org.unicase.ui.esbrowser' version='0.0.1.200808061751'>
      <properties size='3'>
        <property name='artifact.size' value='77084'/>
        <property name='download.size' value='77084'/>
        <property name='download.contentType' value='application/zip'/>
      </properties>
    </artifact>
    <artifact classifier='osgi.bundle' id='org.unicase.model.edit' version='0.0.2.200807221110'>
      <properties size='3'>
        <property name='artifact.size' value='236107'/>
        <property name='download.size' value='236107'/>
        <property name='download.contentType' value='application/zip'/>
      </properties>
    </artifact>
    <artifact classifier='osgi.bundle' id='org.unicase.ui.meeditor' version='0.0.1.200807161219'>
      <properties size='3'>
        <property name='artifact.size' value='45276'/>
        <property name='download.size' value='45276'/>
        <property name='download.contentType' value='application/zip'/>
      </properties>
    </artifact>
    <artifact classifier='osgi.bundle' id='org.unicase.model.edit' version='0.0.2.200808121449'>
      <properties size='3'>
        <property name='artifact.size' value='256060'/>
        <property name='download.size' value='256060'/>
        <property name='download.contentType' value='application/zip'/>
      </properties>
    </artifact>
    <artifact classifier='osgi.bundle' id='org.unicase.ui.tableview' version='0.0.1.200808061731'>
      <properties size='3'>
        <property name='artifact.size' value='16799'/>
        <property name='download.size' value='16799'/>
        <property name='download.contentType' value='application/zip'/>
      </properties>
    </artifact>
    <artifact classifier='osgi.bundle' id='org.unicase.ui.navigator' version='0.0.2.200808121449'>
      <properties size='3'>
        <property name='artifact.size' value='44653'/>
        <property name='download.size' value='44653'/>
        <property name='download.contentType' value='application/zip'/>
      </properties>
    </artifact>
    <artifact classifier='osgi.bundle' id='org.unicase.ui.common' version='0.0.1.200808121449'>
      <properties size='3'>
        <property name='artifact.size' value='32309'/>
        <property name='download.size' value='32309'/>
        <property name='download.contentType' value='application/zip'/>
      </properties>
    </artifact>
    <artifact classifier='osgi.bundle' id='org.unicase.ui.navigator' version='0.0.2.200808061731'>
      <properties size='3'>
        <property name='artifact.size' value='44473'/>
        <property name='download.size' value='44473'/>
        <property name='download.contentType' value='application/zip'/>
      </properties>
    </artifact>
    <artifact classifier='osgi.bundle' id='org.unicase.ui.meeditor' version='0.0.1.200807151618'>
      <properties size='3'>
        <property name='artifact.size' value='45277'/>
        <property name='download.size' value='45277'/>
        <property name='download.contentType' value='application/zip'/>
      </properties>
    </artifact>
    <artifact classifier='osgi.bundle' id='org.unicase.ui.common' version='0.1.0'>
      <properties size='3'>
        <property name='artifact.size' value='33707'/>
        <property name='download.size' value='33707'/>
        <property name='download.contentType' value='application/zip'/>
      </properties>
    </artifact>
    <artifact classifier='osgi.bundle' id='org.unicase.emfstore.esmodel.edit' version='0.0.1.200807161219'>
      <properties size='3'>
        <property name='artifact.size' value='78601'/>
        <property name='download.size' value='78601'/>
        <property name='download.contentType' value='application/zip'/>
      </properties>
    </artifact>
    <artifact classifier='osgi.bundle' id='org.unicase.ui.common' version='0.0.1.200807151608'>
      <properties size='3'>
        <property name='artifact.size' value='7596'/>
        <property name='download.size' value='7596'/>
        <property name='download.contentType' value='application/zip'/>
      </properties>
    </artifact>
    <artifact classifier='osgi.bundle' id='org.unicase.ui.tableview' version='0.0.1.200808061751'>
      <properties size='3'>
        <property name='artifact.size' value='16799'/>
        <property name='download.size' value='16799'/>
        <property name='download.contentType' value='application/zip'/>
      </properties>
    </artifact>
    <artifact classifier='osgi.bundle' id='org.unicase.emfstore.esmodel.edit' version='0.0.1.200807151627'>
      <properties size='3'>
        <property name='artifact.size' value='78601'/>
        <property name='download.size' value='78601'/>
        <property name='download.contentType' value='application/zip'/>
      </properties>
    </artifact>
    <artifact classifier='osgi.bundle' id='org.unicase.ui.meeditor' version='0.0.1.200808061114'>
      <properties size='3'>
        <property name='artifact.size' value='48445'/>
        <property name='download.size' value='48445'/>
        <property name='download.contentType' value='application/zip'/>
      </properties>
    </artifact>
    <artifact classifier='osgi.bundle' id='org.unicase.workspace.edit' version='0.0.1.200808121449'>
      <properties size='3'>
        <property name='artifact.size' value='49213'/>
        <property name='download.size' value='49213'/>
        <property name='download.contentType' value='application/zip'/>
      </properties>
    </artifact>
    <artifact classifier='osgi.bundle' id='org.unicase.model' version='0.0.1.200807151627'>
      <properties size='3'>
        <property name='artifact.size' value='322993'/>
        <property name='download.size' value='322993'/>
        <property name='download.contentType' value='application/zip'/>
      </properties>
    </artifact>
    <artifact classifier='osgi.bundle' id='org.unicase.ui.tableview' version='0.0.1.200808121449'>
      <properties size='3'>
        <property name='artifact.size' value='16828'/>
        <property name='download.size' value='16828'/>
        <property name='download.contentType' value='application/zip'/>
      </properties>
    </artifact>
    <artifact classifier='osgi.bundle' id='org.unicase.ui.meeditor' version='0.0.1.200808061744'>
      <properties size='3'>
        <property name='artifact.size' value='48446'/>
        <property name='download.size' value='48446'/>
        <property name='download.contentType' value='application/zip'/>
      </properties>
    </artifact>
    <artifact classifier='osgi.bundle' id='org.unicase.ui.navigator' version='0.0.2.200807151615'>
      <properties size='3'>
        <property name='artifact.size' value='38145'/>
        <property name='download.size' value='38145'/>
        <property name='download.contentType' value='application/zip'/>
      </properties>
    </artifact>
    <artifact classifier='osgi.bundle' id='org.unicase.ui.test' version='0.0.1.200807241052'>
      <properties size='3'>
        <property name='artifact.size' value='16942'/>
        <property name='download.size' value='16942'/>
        <property name='download.contentType' value='application/zip'/>
      </properties>
    </artifact>
    <artifact classifier='osgi.bundle' id='org.unicase.workspace.edit' version='0.0.1.200808142305'>
      <properties size='3'>
        <property name='artifact.size' value='49498'/>
        <property name='download.size' value='49498'/>
        <property name='download.contentType' value='application/zip'/>
      </properties>
    </artifact>
    <artifact classifier='osgi.bundle' id='org.eclipse.nebula.widgets.cdatetime' version='0.10.0.200806241339'>
      <properties size='3'>
        <property name='artifact.size' value='112347'/>
        <property name='download.size' value='112347'/>
        <property name='download.contentType' value='application/zip'/>
      </properties>
    </artifact>
    <artifact classifier='osgi.bundle' id='org.unicase.emfstore.esmodel' version='0.0.1.200807151618'>
      <properties size='3'>
        <property name='artifact.size' value='102152'/>
        <property name='download.size' value='102152'/>
        <property name='download.contentType' value='application/zip'/>
      </properties>
    </artifact>
    <artifact classifier='osgi.bundle' id='org.unicase.emfstore.esmodel' version='0.0.1.200807151624'>
      <properties size='3'>
        <property name='artifact.size' value='102153'/>
        <property name='download.size' value='102153'/>
        <property name='download.contentType' value='application/zip'/>
      </properties>
    </artifact>
    <artifact classifier='osgi.bundle' id='org.unicase.model.edit' version='0.0.2.200807161219'>
      <properties size='3'>
        <property name='artifact.size' value='251471'/>
        <property name='download.size' value='251471'/>
        <property name='download.contentType' value='application/zip'/>
      </properties>
    </artifact>
    <artifact classifier='osgi.bundle' id='org.unicase.workspace.edit' version='0.0.1.200808061731'>
      <properties size='3'>
        <property name='artifact.size' value='45216'/>
        <property name='download.size' value='45216'/>
        <property name='download.contentType' value='application/zip'/>
      </properties>
    </artifact>
    <artifact classifier='osgi.bundle' id='org.unicase.model.edit' version='0.0.2.200807151627'>
      <properties size='3'>
        <property name='artifact.size' value='251472'/>
        <property name='download.size' value='251472'/>
        <property name='download.contentType' value='application/zip'/>
      </properties>
    </artifact>
    <artifact classifier='osgi.bundle' id='org.unicase.ui.meeditor' version='0.0.1.200807151608'>
      <properties size='3'>
        <property name='artifact.size' value='45277'/>
        <property name='download.size' value='45277'/>
        <property name='download.contentType' value='application/zip'/>
      </properties>
    </artifact>
    <artifact classifier='osgi.bundle' id='org.unicase.model' version='0.0.1.200807241052'>
      <properties size='3'>
        <property name='artifact.size' value='326493'/>
        <property name='download.size' value='326493'/>
        <property name='download.contentType' value='application/zip'/>
      </properties>
    </artifact>
    <artifact classifier='osgi.bundle' id='org.unicase.ui.esbrowser' version='0.0.1.200807151624'>
      <properties size='3'>
        <property name='artifact.size' value='66066'/>
        <property name='download.size' value='66066'/>
        <property name='download.contentType' value='application/zip'/>
      </properties>
    </artifact>
    <artifact classifier='osgi.bundle' id='org.unicase.workspace.edit' version='0.0.1.200807221110'>
      <properties size='3'>
        <property name='artifact.size' value='44950'/>
        <property name='download.size' value='44950'/>
        <property name='download.contentType' value='application/zip'/>
      </properties>
    </artifact>
    <artifact classifier='osgi.bundle' id='org.unicase.emfstore.esmodel.edit' version='0.0.1.200808061744'>
      <properties size='3'>
        <property name='artifact.size' value='103341'/>
        <property name='download.size' value='103341'/>
        <property name='download.contentType' value='application/zip'/>
      </properties>
    </artifact>
    <artifact classifier='osgi.bundle' id='org.unicase.emfstore.esmodel.edit' version='0.0.1'>
      <properties size='3'>
        <property name='artifact.size' value='90404'/>
        <property name='download.size' value='90404'/>
        <property name='download.contentType' value='application/zip'/>
      </properties>
    </artifact>
    <artifact classifier='osgi.bundle' id='org.unicase.workspace.edit' version='0.0.1.200807161219'>
      <properties size='3'>
        <property name='artifact.size' value='26941'/>
        <property name='download.size' value='26941'/>
        <property name='download.contentType' value='application/zip'/>
      </properties>
    </artifact>
    <artifact classifier='osgi.bundle' id='org.unicase.ui.common' version='0.0.1.200807151615'>
      <properties size='3'>
        <property name='artifact.size' value='7595'/>
        <property name='download.size' value='7595'/>
        <property name='download.contentType' value='application/zip'/>
      </properties>
    </artifact>
    <artifact classifier='osgi.bundle' id='org.unicase.workspace' version='0.0.1.200808061114'>
      <properties size='3'>
        <property name='artifact.size' value='64740'/>
        <property name='download.size' value='64740'/>
        <property name='download.contentType' value='application/zip'/>
      </properties>
    </artifact>
    <artifact classifier='osgi.bundle' id='org.unicase.emfstore.esmodel.edit' version='0.0.1.200808061731'>
      <properties size='3'>
        <property name='artifact.size' value='103338'/>
        <property name='download.size' value='103338'/>
        <property name='download.contentType' value='application/zip'/>
      </properties>
    </artifact>
    <artifact classifier='osgi.bundle' id='org.unicase.ui.tableview' version='0.0.1.200807151618'>
      <properties size='3'>
        <property name='artifact.size' value='8551'/>
        <property name='download.size' value='8551'/>
        <property name='download.contentType' value='application/zip'/>
      </properties>
    </artifact>
    <artifact classifier='osgi.bundle' id='org.unicase.ui.tableview' version='0.0.1.200807151615'>
      <properties size='3'>
        <property name='artifact.size' value='8549'/>
        <property name='download.size' value='8549'/>
        <property name='download.contentType' value='application/zip'/>
      </properties>
    </artifact>
    <artifact classifier='osgi.bundle' id='org.unicase.model.edit' version='0.0.1'>
      <properties size='3'>
        <property name='artifact.size' value='243681'/>
        <property name='download.size' value='243681'/>
        <property name='download.contentType' value='application/zip'/>
      </properties>
    </artifact>
    <artifact classifier='osgi.bundle' id='org.unicase.emfstore.esmodel' version='0.0.1.200807151608'>
      <properties size='3'>
        <property name='artifact.size' value='102152'/>
        <property name='download.size' value='102152'/>
        <property name='download.contentType' value='application/zip'/>
      </properties>
    </artifact>
    <artifact classifier='osgi.bundle' id='org.unicase.model.edit' version='0.0.2.200808061114'>
      <properties size='3'>
        <property name='artifact.size' value='240358'/>
        <property name='download.size' value='240358'/>
        <property name='download.contentType' value='application/zip'/>
      </properties>
    </artifact>
    <artifact classifier='osgi.bundle' id='org.unicase.ui.esbrowser' version='0.0.1.200808061731'>
      <properties size='3'>
        <property name='artifact.size' value='77084'/>
        <property name='download.size' value='77084'/>
        <property name='download.contentType' value='application/zip'/>
      </properties>
    </artifact>
    <artifact classifier='osgi.bundle' id='org.unicase.model' version='0.0.1.200807151618'>
      <properties size='3'>
        <property name='artifact.size' value='322993'/>
        <property name='download.size' value='322993'/>
        <property name='download.contentType' value='application/zip'/>
      </properties>
    </artifact>
    <artifact classifier='osgi.bundle' id='org.unicase.model.edit' version='0.0.2.200807151618'>
      <properties size='3'>
        <property name='artifact.size' value='251472'/>
        <property name='download.size' value='251472'/>
        <property name='download.contentType' value='application/zip'/>
      </properties>
    </artifact>
    <artifact classifier='osgi.bundle' id='org.unicase.ui.test' version='0.0.1'>
      <properties size='3'>
        <property name='artifact.size' value='15839'/>
        <property name='download.size' value='15839'/>
        <property name='download.contentType' value='application/zip'/>
      </properties>
    </artifact>
    <artifact classifier='osgi.bundle' id='org.unicase.model' version='0.0.1.200808061114'>
      <properties size='3'>
        <property name='artifact.size' value='338840'/>
        <property name='download.size' value='338840'/>
        <property name='download.contentType' value='application/zip'/>
      </properties>
    </artifact>
    <artifact classifier='osgi.bundle' id='org.unicase.ui.test' version='0.0.1.200807221110'>
      <properties size='3'>
        <property name='artifact.size' value='16941'/>
        <property name='download.size' value='16941'/>
        <property name='download.contentType' value='application/zip'/>
      </properties>
    </artifact>
    <artifact classifier='osgi.bundle' id='org.unicase.emfstore.esmodel' version='0.0.1.200807241052'>
      <properties size='3'>
        <property name='artifact.size' value='144849'/>
        <property name='download.size' value='144849'/>
        <property name='download.contentType' value='application/zip'/>
      </properties>
    </artifact>
    <artifact classifier='osgi.bundle' id='org.unicase.ui.common' version='0.0.1.200807241052'>
      <properties size='3'>
        <property name='artifact.size' value='32355'/>
        <property name='download.size' value='32355'/>
        <property name='download.contentType' value='application/zip'/>
      </properties>
    </artifact>
    <artifact classifier='osgi.bundle' id='org.unicase.emfstore.esmodel.edit' version='0.0.1.200807221110'>
      <properties size='3'>
        <property name='artifact.size' value='78599'/>
        <property name='download.size' value='78599'/>
        <property name='download.contentType' value='application/zip'/>
      </properties>
    </artifact>
    <artifact classifier='osgi.bundle' id='org.unicase.model' version='0.0.1.200807151615'>
      <properties size='3'>
        <property name='artifact.size' value='322993'/>
        <property name='download.size' value='322993'/>
        <property name='download.contentType' value='application/zip'/>
      </properties>
    </artifact>
    <artifact classifier='osgi.bundle' id='org.unicase.ui.esbrowser' version='0.0.1.200807161219'>
      <properties size='3'>
        <property name='artifact.size' value='66065'/>
        <property name='download.size' value='66065'/>
        <property name='download.contentType' value='application/zip'/>
      </properties>
    </artifact>
    <artifact classifier='osgi.bundle' id='org.unicase.model' version='0.0.1.200807171123'>
      <properties size='3'>
        <property name='artifact.size' value='322830'/>
        <property name='download.size' value='322830'/>
        <property name='download.contentType' value='application/zip'/>
      </properties>
    </artifact>
    <artifact classifier='osgi.bundle' id='org.unicase.ui.tableview' version='0.0.1.200807171123'>
      <properties size='3'>
        <property name='artifact.size' value='8550'/>
        <property name='download.size' value='8550'/>
        <property name='download.contentType' value='application/zip'/>
      </properties>
    </artifact>
    <artifact classifier='osgi.bundle' id='org.unicase.ui.common' version='0.0.1'>
      <properties size='3'>
        <property name='artifact.size' value='7092'/>
        <property name='download.size' value='7092'/>
        <property name='download.contentType' value='application/zip'/>
      </properties>
    </artifact>
    <artifact classifier='osgi.bundle' id='org.unicase.emfstore.esmodel.edit' version='0.0.1.200808061114'>
      <properties size='3'>
        <property name='artifact.size' value='103410'/>
        <property name='download.size' value='103410'/>
        <property name='download.contentType' value='application/zip'/>
      </properties>
    </artifact>
    <artifact classifier='org.eclipse.update.feature' id='org.unicase.client' version='0.0.11'>
      <properties size='2'>
        <property name='artifact.size' value='5274'/>
        <property name='download.size' value='5274'/>
      </properties>
    </artifact>
    <artifact classifier='osgi.bundle' id='org.unicase.emfstore' version='0.0.1.200807161219'>
      <properties size='3'>
        <property name='artifact.size' value='3809184'/>
        <property name='download.size' value='3809184'/>
        <property name='download.contentType' value='application/zip'/>
      </properties>
    </artifact>
    <artifact classifier='osgi.bundle' id='org.unicase.ui.common' version='0.0.1.200807151620'>
      <properties size='3'>
        <property name='artifact.size' value='7597'/>
        <property name='download.size' value='7597'/>
        <property name='download.contentType' value='application/zip'/>
      </properties>
    </artifact>
    <artifact classifier='org.eclipse.update.feature' id='org.unicase.client' version='0.0.6'>
      <properties size='2'>
        <property name='artifact.size' value='1140'/>
        <property name='download.size' value='1140'/>
      </properties>
    </artifact>
    <artifact classifier='osgi.bundle' id='org.unicase.ui.esbrowser' version='0.0.1.200808061114'>
      <properties size='3'>
        <property name='artifact.size' value='77076'/>
        <property name='download.size' value='77076'/>
        <property name='download.contentType' value='application/zip'/>
      </properties>
    </artifact>
    <artifact classifier='osgi.bundle' id='org.unicase.workspace' version='0.0.1.200808142305'>
      <properties size='3'>
        <property name='artifact.size' value='65541'/>
        <property name='download.size' value='65541'/>
        <property name='download.contentType' value='application/zip'/>
      </properties>
    </artifact>
    <artifact classifier='org.eclipse.update.feature' id='org.unicase.client' version='0.0.1'>
      <properties size='2'>
        <property name='artifact.size' value='1082'/>
        <property name='download.size' value='1082'/>
      </properties>
    </artifact>
    <artifact classifier='osgi.bundle' id='org.unicase.workspace' version='0.0.1.200808121449'>
      <properties size='3'>
        <property name='artifact.size' value='65540'/>
        <property name='download.size' value='65540'/>
        <property name='download.contentType' value='application/zip'/>
      </properties>
    </artifact>
    <artifact classifier='osgi.bundle' id='org.unicase.ui.tableview' version='0.0.1.200808142305'>
      <properties size='3'>
        <property name='artifact.size' value='21720'/>
        <property name='download.size' value='21720'/>
        <property name='download.contentType' value='application/zip'/>
      </properties>
    </artifact>
    <artifact classifier='osgi.bundle' id='org.unicase.workspace' version='0.0.1.200807161219'>
      <properties size='3'>
        <property name='artifact.size' value='50210'/>
        <property name='download.size' value='50210'/>
        <property name='download.contentType' value='application/zip'/>
      </properties>
    </artifact>
    <artifact classifier='osgi.bundle' id='org.unicase.model' version='0.0.1.200807151620'>
      <properties size='3'>
        <property name='artifact.size' value='322993'/>
        <property name='download.size' value='322993'/>
        <property name='download.contentType' value='application/zip'/>
      </properties>
    </artifact>
    <artifact classifier='osgi.bundle' id='org.unicase.ui.common' version='0.0.1.200807151627'>
      <properties size='3'>
        <property name='artifact.size' value='7596'/>
        <property name='download.size' value='7596'/>
        <property name='download.contentType' value='application/zip'/>
      </properties>
    </artifact>
    <artifact classifier='osgi.bundle' id='org.unicase.model.edit' version='0.0.2.200807151620'>
      <properties size='3'>
        <property name='artifact.size' value='251471'/>
        <property name='download.size' value='251471'/>
        <property name='download.contentType' value='application/zip'/>
      </properties>
    </artifact>
    <artifact classifier='osgi.bundle' id='org.unicase.emfstore.esmodel' version='0.0.1.200807161219'>
      <properties size='3'>
        <property name='artifact.size' value='102162'/>
        <property name='download.size' value='102162'/>
        <property name='download.contentType' value='application/zip'/>
      </properties>
    </artifact>
    <artifact classifier='osgi.bundle' id='org.unicase.emfstore.esmodel' version='0.0.1.200808061751'>
      <properties size='3'>
        <property name='artifact.size' value='149113'/>
        <property name='download.size' value='149113'/>
        <property name='download.contentType' value='application/zip'/>
      </properties>
    </artifact>
    <artifact classifier='org.eclipse.update.feature' id='org.unicase.client' version='0.0.4'>
      <properties size='2'>
        <property name='artifact.size' value='1084'/>
        <property name='download.size' value='1084'/>
      </properties>
    </artifact>
    <artifact classifier='osgi.bundle' id='org.unicase.emfstore' version='0.0.1.200808061114'>
      <properties size='3'>
        <property name='artifact.size' value='3827067'/>
        <property name='download.size' value='3827067'/>
        <property name='download.contentType' value='application/zip'/>
      </properties>
    </artifact>
    <artifact classifier='osgi.bundle' id='org.unicase.workspace' version='0.0.1.qualfier'>
      <properties size='3'>
        <property name='artifact.size' value='49485'/>
        <property name='download.size' value='49485'/>
        <property name='download.contentType' value='application/zip'/>
      </properties>
    </artifact>
    <artifact classifier='org.eclipse.update.feature' id='org.unicase.client' version='0.0.13'>
      <properties size='2'>
        <property name='artifact.size' value='5280'/>
        <property name='download.size' value='5280'/>
      </properties>
    </artifact>
    <artifact classifier='org.eclipse.update.feature' id='org.unicase.client' version='0.0.2'>
      <properties size='2'>
        <property name='artifact.size' value='1059'/>
        <property name='download.size' value='1059'/>
      </properties>
    </artifact>
    <artifact classifier='osgi.bundle' id='org.unicase.ui.meeditor' version='0.0.1.200808121449'>
      <properties size='3'>
        <property name='artifact.size' value='46687'/>
        <property name='download.size' value='46687'/>
        <property name='download.contentType' value='application/zip'/>
      </properties>
    </artifact>
    <artifact classifier='osgi.bundle' id='org.unicase.ui.stem' version='0.0.1.200808061744'>
      <properties size='3'>
        <property name='artifact.size' value='23039'/>
        <property name='download.size' value='23039'/>
        <property name='download.contentType' value='application/zip'/>
      </properties>
    </artifact>
    <artifact classifier='osgi.bundle' id='org.unicase.emfstore' version='0.0.1.200807221110'>
      <properties size='3'>
        <property name='artifact.size' value='3810423'/>
        <property name='download.size' value='3810423'/>
        <property name='download.contentType' value='application/zip'/>
      </properties>
    </artifact>
    <artifact classifier='osgi.bundle' id='org.unicase.ui.navigator' version='0.0.1'>
      <properties size='3'>
        <property name='artifact.size' value='47114'/>
        <property name='download.size' value='47114'/>
        <property name='download.contentType' value='application/zip'/>
      </properties>
    </artifact>
    <artifact classifier='osgi.bundle' id='org.unicase.emfstore' version='0.0.1.200807151627'>
      <properties size='3'>
        <property name='artifact.size' value='3809184'/>
        <property name='download.size' value='3809184'/>
        <property name='download.contentType' value='application/zip'/>
      </properties>
    </artifact>
    <artifact classifier='osgi.bundle' id='org.unicase.emfstore.esmodel' version='0.0.1.200807151620'>
      <properties size='3'>
        <property name='artifact.size' value='102153'/>
        <property name='download.size' value='102153'/>
        <property name='download.contentType' value='application/zip'/>
      </properties>
    </artifact>
    <artifact classifier='osgi.bundle' id='org.unicase.ui.common' version='0.0.1.200808061731'>
      <properties size='3'>
        <property name='artifact.size' value='30894'/>
        <property name='download.size' value='30894'/>
        <property name='download.contentType' value='application/zip'/>
      </properties>
    </artifact>
    <artifact classifier='osgi.bundle' id='org.unicase.ui.esbrowser' version='0.1.0'>
      <properties size='3'>
        <property name='artifact.size' value='78710'/>
        <property name='download.size' value='78710'/>
        <property name='download.contentType' value='application/zip'/>
      </properties>
    </artifact>
    <artifact classifier='osgi.bundle' id='org.unicase.emfstore.esmodel' version='0.0.1.200808061744'>
      <properties size='3'>
        <property name='artifact.size' value='149113'/>
        <property name='download.size' value='149113'/>
        <property name='download.contentType' value='application/zip'/>
      </properties>
    </artifact>
    <artifact classifier='osgi.bundle' id='org.unicase.ui.tableview' version='0.0.1.200808061114'>
      <properties size='3'>
        <property name='artifact.size' value='13096'/>
        <property name='download.size' value='13096'/>
        <property name='download.contentType' value='application/zip'/>
      </properties>
    </artifact>
    <artifact classifier='osgi.bundle' id='org.unicase.ui.esbrowser' version='0.0.1.200807241052'>
      <properties size='3'>
        <property name='artifact.size' value='66165'/>
        <property name='download.size' value='66165'/>
        <property name='download.contentType' value='application/zip'/>
      </properties>
    </artifact>
    <artifact classifier='osgi.bundle' id='org.unicase.ui.stem' version='0.0.1.200807161219'>
      <properties size='3'>
        <property name='artifact.size' value='16499'/>
        <property name='download.size' value='16499'/>
        <property name='download.contentType' value='application/zip'/>
      </properties>
    </artifact>
    <artifact classifier='osgi.bundle' id='org.unicase.ui.common' version='0.0.1.200807161219'>
      <properties size='3'>
        <property name='artifact.size' value='7595'/>
        <property name='download.size' value='7595'/>
        <property name='download.contentType' value='application/zip'/>
      </properties>
    </artifact>
    <artifact classifier='osgi.bundle' id='org.unicase.emfstore.esmodel.edit' version='0.0.1.200807151620'>
      <properties size='3'>
        <property name='artifact.size' value='78598'/>
        <property name='download.size' value='78598'/>
        <property name='download.contentType' value='application/zip'/>
      </properties>
    </artifact>
    <artifact classifier='osgi.bundle' id='org.unicase.ui.esbrowser' version='0.0.1.200807151627'>
      <properties size='3'>
        <property name='artifact.size' value='66065'/>
        <property name='download.size' value='66065'/>
        <property name='download.contentType' value='application/zip'/>
      </properties>
    </artifact>
    <artifact classifier='osgi.bundle' id='org.unicase.model.edit' version='0.0.2.200807151615'>
      <properties size='3'>
        <property name='artifact.size' value='251471'/>
        <property name='download.size' value='251471'/>
        <property name='download.contentType' value='application/zip'/>
      </properties>
    </artifact>
    <artifact classifier='osgi.bundle' id='org.unicase.ui.common' version='0.0.1.200808061744'>
      <properties size='3'>
        <property name='artifact.size' value='30894'/>
        <property name='download.size' value='30894'/>
        <property name='download.contentType' value='application/zip'/>
      </properties>
    </artifact>
    <artifact classifier='osgi.bundle' id='org.unicase.model' version='0.0.1.200808142305'>
      <properties size='3'>
        <property name='artifact.size' value='371041'/>
        <property name='download.size' value='371041'/>
        <property name='download.contentType' value='application/zip'/>
      </properties>
    </artifact>
    <artifact classifier='osgi.bundle' id='org.unicase.ui.meeditor' version='0.0.1.200807151620'>
      <properties size='3'>
        <property name='artifact.size' value='45277'/>
        <property name='download.size' value='45277'/>
        <property name='download.contentType' value='application/zip'/>
      </properties>
    </artifact>
    <artifact classifier='org.eclipse.update.feature' id='org.unicase.client' version='0.0.1'>
      <properties size='2'>
        <property name='artifact.size' value='1102'/>
        <property name='download.size' value='1102'/>
      </properties>
    </artifact>
    <artifact classifier='osgi.bundle' id='org.unicase.ui.meeditor' version='0.0.1'>
      <properties size='3'>
        <property name='artifact.size' value='45187'/>
        <property name='download.size' value='45187'/>
        <property name='download.contentType' value='application/zip'/>
      </properties>
    </artifact>
    <artifact classifier='osgi.bundle' id='org.unicase.model.edit' version='0.0.2'>
      <properties size='3'>
        <property name='artifact.size' value='243680'/>
        <property name='download.size' value='243680'/>
        <property name='download.contentType' value='application/zip'/>
      </properties>
    </artifact>
    <artifact classifier='osgi.bundle' id='org.unicase.ui.esbrowser' version='0.0.1'>
      <properties size='3'>
        <property name='artifact.size' value='64421'/>
        <property name='download.size' value='64421'/>
        <property name='download.contentType' value='application/zip'/>
      </properties>
    </artifact>
    <artifact classifier='osgi.bundle' id='org.unicase.workspace' version='0.0.1.200808061731'>
      <properties size='3'>
        <property name='artifact.size' value='64741'/>
        <property name='download.size' value='64741'/>
        <property name='download.contentType' value='application/zip'/>
      </properties>
    </artifact>
    <artifact classifier='org.eclipse.update.feature' id='org.unicase.client' version='0.0.10'>
      <properties size='2'>
        <property name='artifact.size' value='5275'/>
        <property name='download.size' value='5275'/>
      </properties>
    </artifact>
    <artifact classifier='org.eclipse.update.feature' id='org.unicase.client' version='0.0.3'>
      <properties size='2'>
        <property name='artifact.size' value='1064'/>
        <property name='download.size' value='1064'/>
      </properties>
    </artifact>
    <artifact classifier='osgi.bundle' id='org.unicase.ui.stem' version='0.0.1.200807151608'>
      <properties size='3'>
        <property name='artifact.size' value='16498'/>
        <property name='download.size' value='16498'/>
        <property name='download.contentType' value='application/zip'/>
      </properties>
    </artifact>
    <artifact classifier='osgi.bundle' id='org.unicase.emfstore' version='0.0.1.200808061731'>
      <properties size='3'>
        <property name='artifact.size' value='3827369'/>
        <property name='download.size' value='3827369'/>
        <property name='download.contentType' value='application/zip'/>
      </properties>
    </artifact>
    <artifact classifier='osgi.bundle' id='org.unicase.model.edit' version='0.0.2.200808061744'>
      <properties size='3'>
        <property name='artifact.size' value='240359'/>
        <property name='download.size' value='240359'/>
        <property name='download.contentType' value='application/zip'/>
      </properties>
    </artifact>
    <artifact classifier='osgi.bundle' id='org.eclipse.nebula.widgets.gantchart' version='1.0.0'>
      <properties size='3'>
        <property name='artifact.size' value='167839'/>
        <property name='download.size' value='167839'/>
        <property name='download.contentType' value='application/zip'/>
      </properties>
    </artifact>
    <artifact classifier='osgi.bundle' id='org.unicase.emfstore' version='0.0.1.200807151608'>
      <properties size='3'>
        <property name='artifact.size' value='3809184'/>
        <property name='download.size' value='3809184'/>
        <property name='download.contentType' value='application/zip'/>
      </properties>
    </artifact>
    <artifact classifier='osgi.bundle' id='org.unicase.ui.test' version='0.0.1.qualfier'>
      <properties size='3'>
        <property name='artifact.size' value='16545'/>
        <property name='download.size' value='16545'/>
        <property name='download.contentType' value='application/zip'/>
      </properties>
    </artifact>
    <artifact classifier='osgi.bundle' id='org.unicase.ui.navigator' version='0.0.2.200807151620'>
      <properties size='3'>
        <property name='artifact.size' value='38146'/>
        <property name='download.size' value='38146'/>
        <property name='download.contentType' value='application/zip'/>
      </properties>
    </artifact>
  </artifacts>
</repository>
